CHANGES.rst
DESCRIPTION.rst
LICENSE
MANIFEST.in
README.md
setup.py
src/ldc_pdf/__init__.py
src/ldc_pdf/class_lister.py
src/ldc_pdf.egg-info/PKG-INFO
src/ldc_pdf.egg-info/SOURCES.txt
src/ldc_pdf.egg-info/dependency_links.txt
src/ldc_pdf.egg-info/entry_points.txt
src/ldc_pdf.egg-info/requires.txt
src/ldc_pdf.egg-info/top_level.txt
src/ldc_pdf/pretrain/__init__.py
src/ldc_pdf/pretrain/_pdf.py