Metadata-Version: 2.1
Name: ldc-pdf
Version: 0.0.4
Summary: Python3 library that adds PDF support to the llm-dataset-converter library.
Home-page: https://github.com/waikato-llm/ldc-pdf
Author: Peter Reutemann
Author-email: fracpete@waikato.ac.nz
License: MIT License
Classifier: Development Status :: 4 - Beta
Classifier: License :: OSI Approved :: MIT License
Classifier: Topic :: Scientific/Engineering :: Artificial Intelligence
Classifier: Programming Language :: Python :: 3
License-File: LICENSE
